{
  "dataset_name": "narrativeqa",
  "rag_target": "standard",
  "category": "benchmark",
  "generated_at": "2026-02-06T20:19:16.429972",
  "total_questions": 2750,
  "summary": {
    "total_tested": 2750,
    "total_answered": 0,
    "total_correct": 0,
    "total_errors": 2750,
    "avg_f1": 0.0,
    "avg_latency_ms": 0,
    "answer_rate": "0.0%",
    "error_type": "fetch is not defined",
    "data_present_in_db": "YES - ingested in Supabase",
    "status": "ALL_ERRORED"
  },
  "questions_sample": [
    {
      "run_id": "test-retrieval-narrativeqa-1770386823831-6iyn91",
      "item_index": 6825,
      "question": "{'text': 'Who is Mark Hunter?', 'tokens': ['Who', 'is', 'Mark', 'Hunter', '?']}",
      "expected_answer": "He is a high school student in Phoenix.",
      "actual_answer": null,
      "error": "fetch is not defined",
      "rag_type": "standard",
      "status": "error"
    },
    {
      "run_id": "test-retrieval-narrativeqa-1770386823831-6iyn91",
      "item_index": 6826,
      "question": "{'text': 'Where does this radio station take place?', 'tokens': ['Where', 'does', 'this', 'radio', 'station', 'take', 'place', '?']}",
      "expected_answer": "It takes place in Mark's parents basement. ",
      "actual_answer": null,
      "error": "fetch is not defined",
      "rag_type": "standard",
      "status": "error"
    },
    {
      "run_id": "test-retrieval-narrativeqa-1770386823831-6iyn91",
      "item_index": 6827,
      "question": "{'text': \"Why do more students tune into Mark's show?\", 'tokens': ['Why', 'do', 'more', 'students', 'tune', 'into', 'Mark', 's', 'show', '?']}",
      "expected_answer": "Mark talks about what goes on at school and in the community.",
      "actual_answer": null,
      "error": "fetch is not defined",
      "rag_type": "standard",
      "status": "error"
    },
    {
      "run_id": "test-retrieval-narrativeqa-1770386823831-6iyn91",
      "item_index": 6828,
      "question": "{'text': 'Who commits suicide?', 'tokens': ['Who', 'commits', 'suicide', '?']}",
      "expected_answer": "Malcolm.",
      "actual_answer": null,
      "error": "fetch is not defined",
      "rag_type": "standard",
      "status": "error"
    },
    {
      "run_id": "test-retrieval-narrativeqa-1770386823831-6iyn91",
      "item_index": 6829,
      "question": "{'text': 'What does Paige jam into her microwave?', 'tokens': ['What', 'does', 'Paige', 'jam', 'into', 'her', 'microwave', '?']}",
      "expected_answer": "She jams her medals and accolades. ",
      "actual_answer": null,
      "error": "fetch is not defined",
      "rag_type": "standard",
      "status": "error"
    },
    {
      "run_id": "test-retrieval-narrativeqa-1770386823831-6iyn91",
      "item_index": 6830,
      "question": "{'text': 'What does Mark do with his radio station?', 'tokens': ['What', 'does', 'Mark', 'do', 'with', 'his', 'radio', 'station', '?']}",
      "expected_answer": "He dismantles it and attaches it to his mother's jeep.",
      "actual_answer": null,
      "error": "fetch is not defined",
      "rag_type": "standard",
      "status": "error"
    },
    {
      "run_id": "test-retrieval-narrativeqa-1770386823831-6iyn91",
      "item_index": 6831,
      "question": "{'text': 'What does Mark tell the protesting students?', 'tokens': ['What', 'does', 'Mark', 'tell', 'the', 'protesting', 'students', '?']}",
      "expected_answer": "He tells them to make their own future.",
      "actual_answer": null,
      "error": "fetch is not defined",
      "rag_type": "standard",
      "status": "error"
    },
    {
      "run_id": "test-retrieval-narrativeqa-1770386823831-6iyn91",
      "item_index": 6832,
      "question": "{'text': 'Who gets arrested?', 'tokens': ['Who', 'gets', 'arrested', '?']}",
      "expected_answer": "Mark and Nora.",
      "actual_answer": null,
      "error": "fetch is not defined",
      "rag_type": "standard",
      "status": "error"
    },
    {
      "run_id": "test-retrieval-narrativeqa-1770386823831-6iyn91",
      "item_index": 6833,
      "question": "{'text': 'What does the radio show cause?', 'tokens': ['What', 'does', 'the', 'radio', 'show', 'cause', '?']}",
      "expected_answer": "It causes trouble. ",
      "actual_answer": null,
      "error": "fetch is not defined",
      "rag_type": "standard",
      "status": "error"
    },
    {
      "run_id": "test-retrieval-narrativeqa-1770386823831-6iyn91",
      "item_index": 6834,
      "question": "{'text': 'Where does Mark Broadcast his station from?', 'tokens': ['Where', 'does', 'Mark', 'Broadcast', 'his', 'station', 'from', '?']}",
      "expected_answer": "Parent's Basement",
      "actual_answer": null,
      "error": "fetch is not defined",
      "rag_type": "standard",
      "status": "error"
    },
    {
      "run_id": "test-retrieval-narrativeqa-1770386823831-6iyn91",
      "item_index": 6835,
      "question": "{'text': \"What is Mark's only outlet?\", 'tokens': ['What', 'is', 'Mark', 's', 'only', 'outlet', '?']}",
      "expected_answer": "His Radio station ",
      "actual_answer": null,
      "error": "fetch is not defined",
      "rag_type": "standard",
      "status": "error"
    },
    {
      "run_id": "test-retrieval-narrativeqa-1770386823831-6iyn91",
      "item_index": 6836,
      "question": "{'text': \"What is Mark's Pirate Station's theme song ?\", 'tokens': ['What', 'is', 'Mark', 's', 'Pirate', 'Station', 's', 'theme', 'song', '?']}",
      "expected_answer": "Everybody Knows",
      "actual_answer": null,
      "error": "fetch is not defined",
      "rag_type": "standard",
      "status": "error"
    },
    {
      "run_id": "test-retrieval-narrativeqa-1770386823831-6iyn91",
      "item_index": 6837,
      "question": "{'text': 'What is Nora Diniro to Mark?', 'tokens': ['What', 'is', 'Nora', 'Diniro', 'to', 'Mark', '?']}",
      "expected_answer": "Fellow Student",
      "actual_answer": null,
      "error": "fetch is not defined",
      "rag_type": "standard",
      "status": "error"
    },
    {
      "run_id": "test-retrieval-narrativeqa-1770386823831-6iyn91",
      "item_index": 6838,
      "question": "{'text': 'Why does Nora track Mark down?', 'tokens': ['Why', 'does', 'Nora', 'track', 'Mark', 'down', '?']}",
      "expected_answer": "Malcom' s suicide",
      "actual_answer": null,
      "error": "fetch is not defined",
      "rag_type": "standard",
      "status": "error"
    },
    {
      "run_id": "test-retrieval-narrativeqa-1770386823831-6iyn91",
      "item_index": 6839,
      "question": "{'text': 'What does Mark urge his listeners to do?', 'tokens': ['What', 'does', 'Mark', 'urge', 'his', 'listeners', 'to', 'do', '?']}",
      "expected_answer": "Do something about their problems.",
      "actual_answer": null,
      "error": "fetch is not defined",
      "rag_type": "standard",
      "status": "error"
    },
    {
      "run_id": "test-retrieval-narrativeqa-1770386823831-6iyn91",
      "item_index": 6840,
      "question": "{'text': \"Who is called in to investigate Mark's radio station? \", 'tokens': ['Who', 'is', 'called', 'in', 'to', 'investigate', 'Mark', 's', 'radio', 'station', '?']}",
      "expected_answer": "The FCC",
      "actual_answer": null,
      "error": "fetch is not defined",
      "rag_type": "standard",
      "status": "error"
    },
    {
      "run_id": "test-retrieval-narrativeqa-1770386823831-6iyn91",
      "item_index": 6841,
      "question": "{'text': 'Why did the principal commit fraud?', 'tokens': ['Why', 'did', 'the', 'principal', 'commit', 'fraud', '?']}",
      "expected_answer": "To retain government funding",
      "actual_answer": null,
      "error": "fetch is not defined",
      "rag_type": "standard",
      "status": "error"
    },
    {
      "run_id": "test-retrieval-narrativeqa-1770386823831-6iyn91",
      "item_index": 6842,
      "question": "{'text': 'What did the principal do with poor achieving students?', 'tokens': ['What', 'did', 'the', 'principal', 'do', 'with', 'poor', 'achieving', 'students', '?']}",
      "expected_answer": "Expelled them",
      "actual_answer": null,
      "error": "fetch is not defined",
      "rag_type": "standard",
      "status": "error"
    },
    {
      "run_id": "test-retrieval-narrativeqa-1770386823831-6iyn91",
      "item_index": 6843,
      "question": "{'text': 'Who drives the Jeep while Mark broadcasts? ', 'tokens': ['Who', 'drives', 'the', 'Jeep', 'while', 'Mark', 'broadcasts', '?']}",
      "expected_answer": "Nora",
      "actual_answer": null,
      "error": "fetch is not defined",
      "rag_type": "standard",
      "status": "error"
    },
    {
      "run_id": "test-retrieval-narrativeqa-1770386823831-6iyn91",
      "item_index": 6844,
      "question": "{'text': 'Where does Mark go to school?', 'tokens': ['Where', 'does', 'Mark', 'go', 'to', 'school', '?']}",
      "expected_answer": "Phoenix, Arizona.",
      "actual_answer": null,
      "error": "fetch is not defined",
      "rag_type": "standard",
      "status": "error"
    },
    {
      "run_id": "test-retrieval-narrativeqa-1770386823831-6iyn91",
      "item_index": 6845,
      "question": "{'text': 'Where does Mark broadcast his radio station?', 'tokens': ['Where', 'does', 'Mark', 'broadcast', 'his', 'radio', 'station', '?']}",
      "expected_answer": "In his parent's basement.",
      "actual_answer": null,
      "error": "fetch is not defined",
      "rag_type": "standard",
      "status": "error"
    },
    {
      "run_id": "test-retrieval-narrativeqa-1770386823831-6iyn91",
      "item_index": 6846,
      "question": "{'text': 'What does Mark use the song Everybody Knows for?', 'tokens': ['What', 'does', 'Mark', 'use', 'the', 'song', 'Everybody', 'Knows', 'for', '?']}",
      "expected_answer": "His radio stations theme song.",
      "actual_answer": null,
      "error": "fetch is not defined",
      "rag_type": "standard",
      "status": "error"
    },
    {
      "run_id": "test-retrieval-narrativeqa-1770386823831-6iyn91",
      "item_index": 6847,
      "question": "{'text': 'When Harry tries to reason with Malcolm, what does Malcolm do?', 'tokens': ['When', 'Harry', 'tries', 'to', 'reason', 'with', 'Malcolm', ',', 'what', 'does', 'Malcolm', 'do', '?']}",
      "expected_answer": "Commits suicide.",
      "actual_answer": null,
      "error": "fetch is not defined",
      "rag_type": "standard",
      "status": "error"
    },
    {
      "run_id": "test-retrieval-narrativeqa-1770386823831-6iyn91",
      "item_index": 6848,
      "question": "{'text': 'What does Paige do with her medals?', 'tokens': ['What', 'does', 'Paige', 'do', 'with', 'her', 'medals', '?']}",
      "expected_answer": "Puts them in the microwave.",
      "actual_answer": null,
      "error": "fetch is not defined",
      "rag_type": "standard",
      "status": "error"
    },
    {
      "run_id": "test-retrieval-narrativeqa-1770386823831-6iyn91",
      "item_index": 6849,
      "question": "{'text': 'How does Paige get injured?', 'tokens': ['How', 'does', 'Paige', 'get', 'injured', '?']}",
      "expected_answer": "When the microwave explodes.",
      "actual_answer": null,
      "error": "fetch is not defined",
      "rag_type": "standard",
      "status": "error"
    },
    {
      "run_id": "test-retrieval-narrativeqa-1770386823831-6iyn91",
      "item_index": 6850,
      "question": "{'text': 'Why is the FCC called?', 'tokens': ['Why', 'is', 'the', 'FCC', 'called', '?']}",
      "expected_answer": "To investigate the radio show.",
      "actual_answer": null,
      "error": "fetch is not defined",
      "rag_type": "standard",
      "status": "error"
    },
    {
      "run_id": "test-retrieval-narrativeqa-1770386823831-6iyn91",
      "item_index": 6851,
      "question": "{'text': 'What was the principle doing with the problem students?', 'tokens': ['What', 'was', 'the', 'principle', 'doing', 'with', 'the', 'problem', 'students', '?']}",
      "expected_answer": "Expelling them.",
      "actual_answer": null,
      "error": "fetch is not defined",
      "rag_type": "standard",
      "status": "error"
    },
    {
      "run_id": "test-retrieval-narrativeqa-1770386823831-6iyn91",
      "item_index": 6852,
      "question": "{'text': 'Who is chasing Mark and Nora in the jeep?', 'tokens': ['Who', 'is', 'chasing', 'Mark', 'and', 'Nora', 'in', 'the', 'jeep', '?']}",
      "expected_answer": "The cops and the FCC.",
      "actual_answer": null,
      "error": "fetch is not defined",
      "rag_type": "standard",
      "status": "error"
    },
    {
      "run_id": "test-retrieval-narrativeqa-1770386823831-6iyn91",
      "item_index": 6853,
      "question": "{'text': 'What are the students doing when Mark and Nora drive up?', 'tokens': ['What', 'are', 'the', 'students', 'doing', 'when', 'Mark', 'and', 'Nora', 'drive', 'up', '?']}",
      "expected_answer": "Protesting.",
      "actual_answer": null,
      "error": "fetch is not defined",
      "rag_type": "standard",
      "status": "error"
    },
    {
      "run_id": "test-retrieval-narrativeqa-1770386823831-6iyn91",
      "item_index": 6854,
      "question": "{'text': 'Who does Maskull accept an invitation from?', 'tokens': ['Who', 'does', 'Maskull', 'accept', 'an', 'invitation', 'from', '?']}",
      "expected_answer": "Krag",
      "actual_answer": null,
      "error": "fetch is not defined",
      "rag_type": "standard",
      "status": "error"
    },
    {
      "run_id": "test-retrieval-narrativeqa-1770386823831-6iyn91",
      "item_index": 6855,
      "question": "{'text': 'Who is Krag an acquaintance of?', 'tokens': ['Who', 'is', 'Krag', 'an', 'acquaintance', 'of', '?']}",
      "expected_answer": "Nightspore",
      "actual_answer": null,
      "error": "fetch is not defined",
      "rag_type": "standard",
      "status": "error"
    },
    {
      "run_id": "test-retrieval-narrativeqa-1770386823831-6iyn91",
      "item_index": 6856,
      "question": "{'text': 'Where is Maskull traveling to?', 'tokens': ['Where', 'is', 'Maskull', 'traveling', 'to', '?']}",
      "expected_answer": "Tormance",
      "actual_answer": null,
      "error": "fetch is not defined",
      "rag_type": "standard",
      "status": "error"
    },
    {
      "run_id": "test-retrieval-narrativeqa-1770386823831-6iyn91",
      "item_index": 6857,
      "question": "{'text': 'When Maskull wakes up in Tormance, how many of his friends are with him?', 'tokens': ['When', 'Maskull', 'wakes', 'up', 'in', 'Tormance', ',', 'how', 'many', 'of', 'his', 'friends', 'are', '",
      "expected_answer": "None",
      "actual_answer": null,
      "error": "fetch is not defined",
      "rag_type": "standard",
      "status": "error"
    },
    {
      "run_id": "test-retrieval-narrativeqa-1770386823831-6iyn91",
      "item_index": 6858,
      "question": "{'text': 'Who does Maskull realize he really is?', 'tokens': ['Who', 'does', 'Maskull', 'realize', 'he', 'really', 'is', '?']}",
      "expected_answer": "Nightspore",
      "actual_answer": null,
      "error": "fetch is not defined",
      "rag_type": "standard",
      "status": "error"
    },
    {
      "run_id": "test-retrieval-narrativeqa-1770386823831-6iyn91",
      "item_index": 6859,
      "question": "{'text': 'Who does Krag claim that he is none as on Earth?', 'tokens': ['Who', 'does', 'Krag', 'claim', 'that', 'he', 'is', 'none', 'as', 'on', 'Earth', '?']}",
      "expected_answer": "Pain",
      "actual_answer": null,
      "error": "fetch is not defined",
      "rag_type": "standard",
      "status": "error"
    },
    {
      "run_id": "test-retrieval-narrativeqa-1770386823831-6iyn91",
      "item_index": 6860,
      "question": "{'text': 'What kind of ship does Maskull travel in?', 'tokens': ['What', 'kind', 'of', 'ship', 'does', 'Maskull', 'travel', 'in', '?']}",
      "expected_answer": "A crystal ship",
      "actual_answer": null,
      "error": "fetch is not defined",
      "rag_type": "standard",
      "status": "error"
    },
    {
      "run_id": "test-retrieval-narrativeqa-1770386823831-6iyn91",
      "item_index": 6861,
      "question": "{'text': 'Where is the abandoned observatory located?', 'tokens': ['Where', 'is', 'the', 'abandoned', 'observatory', 'located', '?']}",
      "expected_answer": "In Scotland",
      "actual_answer": null,
      "error": "fetch is not defined",
      "rag_type": "standard",
      "status": "error"
    },
    {
      "run_id": "test-retrieval-narrativeqa-1770386823831-6iyn91",
      "item_index": 6862,
      "question": "{'text': 'Whose death does he learn is coming soon?', 'tokens': ['Whose', 'death', 'does', 'he', 'learn', 'is', 'coming', 'soon', '?']}",
      "expected_answer": "his own",
      "actual_answer": null,
      "error": "fetch is not defined",
      "rag_type": "standard",
      "status": "error"
    },
    {
      "run_id": "test-retrieval-narrativeqa-1770386823831-6iyn91",
      "item_index": 6863,
      "question": "{'text': 'Who gives the last revelation?', 'tokens': ['Who', 'gives', 'the', 'last', 'revelation', '?']}",
      "expected_answer": "Krag",
      "actual_answer": null,
      "error": "fetch is not defined",
      "rag_type": "standard",
      "status": "error"
    },
    {
      "run_id": "test-retrieval-narrativeqa-1770386823831-6iyn91",
      "item_index": 6864,
      "question": "{'text': 'Why does Maskull accept an invitation Krag to go to Tormance?', 'tokens': ['Why', 'does', 'Maskull', 'accept', 'an', 'invitation', 'Krag', 'to', 'go', 'to', 'Tormance', '?']}",
      "expected_answer": "He longs for adventure. ",
      "actual_answer": null,
      "error": "fetch is not defined",
      "rag_type": "standard",
      "status": "error"
    },
    {
      "run_id": "test-retrieval-narrativeqa-1770386823831-6iyn91",
      "item_index": 6865,
      "question": "{'text': 'Who is Krag to Maskull?', 'tokens': ['Who', 'is', 'Krag', 'to', 'Maskull', '?']}",
      "expected_answer": "A acquaintance of his friend Nightspore.",
      "actual_answer": null,
      "error": "fetch is not defined",
      "rag_type": "standard",
      "status": "error"
    },
    {
      "run_id": "test-retrieval-narrativeqa-1770386823831-6iyn91",
      "item_index": 6866,
      "question": "{'text': 'What sort of ship did Maskull, Krag, and Nightspore set of in?', 'tokens': ['What', 'sort', 'of', 'ship', 'did', 'Maskull', ',', 'Krag', ',', 'and', 'Nightspore', 'set', 'of', 'in', '?']}",
      "expected_answer": "A crystal ship",
      "actual_answer": null,
      "error": "fetch is not defined",
      "rag_type": "standard",
      "status": "error"
    },
    {
      "run_id": "test-retrieval-narrativeqa-1770386823831-6iyn91",
      "item_index": 6867,
      "question": "{'text': 'Where did not crystal ship come from?', 'tokens': ['Where', 'did', 'not', 'crystal', 'ship', 'come', 'from', '?']}",
      "expected_answer": "From an abandoned observatory in Scotland.",
      "actual_answer": null,
      "error": "fetch is not defined",
      "rag_type": "standard",
      "status": "error"
    },
    {
      "run_id": "test-retrieval-narrativeqa-1770386823831-6iyn91",
      "item_index": 6868,
      "question": "{'text': 'Who is missing from the ship when Maskull wakes?', 'tokens': ['Who', 'is', 'missing', 'from', 'the', 'ship', 'when', 'Maskull', 'wakes', '?']}",
      "expected_answer": "Krag and Nightspore.",
      "actual_answer": null,
      "error": "fetch is not defined",
      "rag_type": "standard",
      "status": "error"
    },
    {
      "run_id": "test-retrieval-narrativeqa-1770386823831-6iyn91",
      "item_index": 6869,
      "question": "{'text': 'How many people does Maskull usually see in the lands he travels?', 'tokens': ['How', 'many', 'people', 'does', 'Maskull', 'usually', 'see', 'in', 'the', 'lands', 'he', 'travels', '?']}",
      "expected_answer": "Not more than 1 or 2.",
      "actual_answer": null,
      "error": "fetch is not defined",
      "rag_type": "standard",
      "status": "error"
    },
    {
      "run_id": "test-retrieval-narrativeqa-1770386823831-6iyn91",
      "item_index": 6870,
      "question": "{'text': 'What happens to the people Maskull meets in his travels to various lands?', 'tokens': ['What', 'happens', 'to', 'the', 'people', 'Maskull', 'meets', 'in', 'his', 'travels', 'to', 'various', ",
      "expected_answer": "They usually die by his hand or anothers.",
      "actual_answer": null,
      "error": "fetch is not defined",
      "rag_type": "standard",
      "status": "error"
    },
    {
      "run_id": "test-retrieval-narrativeqa-1770386823831-6iyn91",
      "item_index": 6871,
      "question": "{'text': 'Whom is known on Earth as Pain?', 'tokens': ['Whom', 'is', 'known', 'on', 'Earth', 'as', 'Pain', '?']}",
      "expected_answer": "Krag.",
      "actual_answer": null,
      "error": "fetch is not defined",
      "rag_type": "standard",
      "status": "error"
    },
    {
      "run_id": "test-retrieval-narrativeqa-1770386823831-6iyn91",
      "item_index": 6872,
      "question": "{'text': 'Maskull learns that he is also what character? ', 'tokens': ['Maskull', 'learns', 'that', 'he', 'is', 'also', 'what', 'character', '?']}",
      "expected_answer": "Nightspore.",
      "actual_answer": null,
      "error": "fetch is not defined",
      "rag_type": "standard",
      "status": "error"
    },
    {
      "run_id": "test-retrieval-narrativeqa-1770386823831-6iyn91",
      "item_index": 6873,
      "question": "{'text': 'What country does Maskull, Krag, and Nightspore set off from?', 'tokens': ['What', 'country', 'does', 'Maskull', ',', 'Krag', ',', 'and', 'Nightspore', 'set', 'off', 'from', '?']}",
      "expected_answer": "Scotland",
      "actual_answer": null,
      "error": "fetch is not defined",
      "rag_type": "standard",
      "status": "error"
    },
    {
      "run_id": "test-retrieval-narrativeqa-1770386823831-6iyn91",
      "item_index": 6874,
      "question": "{'text': 'On average, how many people does Maskull normally meet when traveling?', 'tokens': ['On', 'average', ',', 'how', 'many', 'people', 'does', 'Maskull', 'normally', 'meet', 'when', 'traveling',",
      "expected_answer": "One or two",
      "actual_answer": null,
      "error": "fetch is not defined",
      "rag_type": "standard",
      "status": "error"
    }
  ],
  "data_verification": {
    "ingestion_status": "completed",
    "ingestion_error": "unknown",
    "ingestion_run_id": "",
    "items_ingested": 700,
    "ingested_at": "2026-02-06T21:10:42.187068",
    "supabase_ready": true,
    "pinecone_ready": false,
    "neo4j_ready": false,
    "exec_id": "9932",
    "ingestion_method": "BENCHMARK - Dataset Ingestion Pipeline",
    "pages_ingested": 10
  },
  "last_updated": "2026-02-06T21:10:42.187087"
}